<!-- Last project change: 2015-03-22 10:42:03 (2015-03-22 17:42:03) -->
<PrjQlikViewProject>
  <GLOBAL>
    <AllPropertiesFileName>AllProperties.xml</AllPropertiesFileName>
    <DocBinaryFileName>DocBinary.dat</DocBinaryFileName>
    <DocInternalsFileName>DocInternals.xml</DocInternalsFileName>
    <DocPropertiesFileName>DocProperties.xml</DocPropertiesFileName>
    <LoadScriptFileName>LoadScript.txt</LoadScriptFileName>
    <ModuleFileName>Module.txt</ModuleFileName>
    <TopLayoutFileName>TopLayout.xml</TopLayoutFileName>
  </GLOBAL>
  <SHEETS>
    <PrjSheetProperties>
      <SheetId>Document\SH01</SheetId>
      <IsActive>true</IsActive>
      <ChildObjects>
        <PrjFrameParentDef>
          <ObjectId>Document\LB01_839557978</ObjectId>
          <Rect>
            <Left>1581</Left>
            <Top>222</Top>
            <Width>1172</Width>
            <Height>900</Height>
          </Rect>
          <MinimizedRect>
            <Left>0</Left>
            <Top>0</Top>
            <Width>297</Width>
            <Height>102</Height>
          </MinimizedRect>
          <ShowMode>1</ShowMode>
          <ZedLevel>0</ZedLevel>
        </PrjFrameParentDef>
        <PrjFrameParentDef>
          <ObjectId>Document\LB02_989753370</ObjectId>
          <Rect>
            <Left>1097</Left>
            <Top>216</Top>
            <Width>450</Width>
            <Height>900</Height>
          </Rect>
          <MinimizedRect>
            <Left>0</Left>
            <Top>0</Top>
            <Width>297</Width>
            <Height>102</Height>
          </MinimizedRect>
          <ShowMode>1</ShowMode>
          <ZedLevel>0</ZedLevel>
        </PrjFrameParentDef>
      </ChildObjects>
    </PrjSheetProperties>
  </SHEETS>
  <REPORTS></REPORTS>
  <ContainerMembers></ContainerMembers>
</PrjQlikViewProject>
